UQit/__init__.py
UQit/analyticTestFuncs.py
UQit/gpr_torch.py
UQit/lagInt.py
UQit/linAlg.py
UQit/nodes.py
UQit/pce.py
UQit/ppce.py
UQit/reshaper.py
UQit/sampling.py
UQit/sobol.py
UQit/stats.py
UQit/surr2surr.py
UQit/write.py
UQit-1.0.2.dist-info/LICENSE
UQit-1.0.2.dist-info/METADATA
UQit-1.0.2.dist-info/WHEEL
UQit-1.0.2.dist-info/top_level.txt
UQit-1.0.2.dist-info/RECORD
