Metadata-Version: 2.1
Name: UQit
Version: 1.0.2
Summary: A Python Package for Uncertainty Quantification (UQ) in Computational Fluid Dynamics (CFD)
Home-page: https://github.com/KTH-Nek5000/UQit
Author: Saleh Rezaeiravesh
Author-email: salehr@kth.se
License: UNKNOWN
Platform: UNKNOWN
Classifier: Programming Language :: Python :: 3
Classifier: License :: OSI Approved :: Mozilla Public License 2.0 (MPL 2.0)
Classifier: Operating System :: OS Independent
Requires-Python: >=3.6
